pcawg_colors/__init__.py
pcawg_colors/pcawg_colors.py
pcawg_colors-1.0.0.dist-info/METADATA
pcawg_colors-1.0.0.dist-info/WHEEL
pcawg_colors-1.0.0.dist-info/top_level.txt
pcawg_colors-1.0.0.dist-info/RECORD
