Metadata-Version: 2.1
Name: pcawg_colors
Version: 1.0.0
Summary: Colors used in PCAWG figures
Home-page: https://github.com/sudogene/pcawg_colors
Author: Andy Wu
Author-email: andywubby@gmail.com
License: BSD 2-clause
Platform: UNKNOWN
Classifier: Programming Language :: Python :: 3
